41_Verilog/f16_fmac_normal_no_grs.v
module f16_fmac_normal_no_grs (
    input      [15:0] x,
    input      [15:0] y,
    input      [15:0] z,
    output reg [15:0] result
);

// parameter == const
parameter NORMAL    = 2'b00;
parameter OVERFLOW  = 2'b01;
parameter UNDERFLOW = 2'b10;
parameter BIAS      = 4'd15;

// Seperate (Sign(1-bit) / Expnent(5-bit) / Mantissa(10-bit))
wire sign_x = x[15];
wire sign_y = y[15];
wire sign_z = z[15];

wire [4:0] expo_x = x[14:10];
wire [4:0] expo_y = y[14:10];
wire [5:0] expo_z = {1'b0, z[14:10]} + {1'b0, BIAS}; // 6-bit(Exponent + Bias)

wire [9:0] mant_x = x[9:0];
wire [9:0] mant_y = y[9:0];
wire [9:0] mant_z = z[9:0];

// Significand(11-bit / 22-bit) : Hidden 1-bit + Mantissa
wire [10:0] sigf_x = {1'b1, mant_x};
wire [10:0] sigf_y = {1'b1, mant_y};
wire [21:0] sigf_z = (expo_z == {1'b0, BIAS}) ? 22'd0 : {1'b1, mant_z, 11'd0};

// Zero = (? x 0) or (0 x ?) -> t_falg = true
wire t_flag = (expo_x == 5'd0 || expo_y == 5'd0);

// Multiply: significand_x * significand_y (22-bit)
wire [21:0] mult = sigf_x * sigf_y;

// Temp Sign
wire sign_t = sign_x ^ sign_y;

// Temp Exponent and Significand
reg [5:0] expo_t;
reg expo_add;
reg [21:0] aligned_t;
always@(*) begin
    if(t_flag) begin
        expo_t = 6'd0;
        aligned_t = 22'd0;
    end else begin
        if(mult[21]) begin
            aligned_t = mult;
            expo_add = 1'b1;
        end else begin
            aligned_t = mult << 1;
            expo_add = 1'b0;
        end
        expo_t = expo_x + expo_y + expo_add;
    end
end

// Magnitude Compare : {Exp_t + aligned_t} <> {Exp_z + sigf_z}
wire [27:0] mag_t = {expo_t, aligned_t};
wire [27:0] mag_z = {expo_z, sigf_z};
wire great_value = (mag_t >= mag_z);

// Sign
wire sign_xor = sign_t ^ sign_z;
wire sign = (sign_t == sign_z) ? sign_t : 
            (great_value) ? sign_t : sign_z;

// Large Magnitude: l, Small Magnitude: s
wire [5:0]  expo_l, expo_s;
wire [21:0] sigf_l, sigf_s;
assign expo_l = great_value ? expo_t : expo_z;
assign expo_s = great_value ? expo_z : expo_t;
assign sigf_l = great_value ? aligned_t : sigf_z;
assign sigf_s = great_value ? sigf_z : aligned_t;

// Exponent Difference(6-bit)
wire [5:0] expo_diff = expo_l - expo_s;

// Aligning
wire [21:0] aligned_l, aligned_s;
assign aligned_l = sigf_l;
assign aligned_s = (expo_diff >= 6'd21) ? 22'd0 : sigf_s >> expo_diff;

// 2's Complement and Add
wire [22:0] aligned = sign_xor ? (aligned_l - aligned_s) : (aligned_l + aligned_s);

// aligned == 0 -> Zero
wire flag_zero = (aligned == 23'd0);

// Leading Zero Counter(23-bit)
wire carry = aligned[22];
reg[4:0] shift_exp;
always@(*) begin
    if      (aligned[21]) shift_exp = 5'd0;
    else if (aligned[20]) shift_exp = 5'd1;
    else if (aligned[19]) shift_exp = 5'd2;
    else if (aligned[18]) shift_exp = 5'd3;
    else if (aligned[17]) shift_exp = 5'd4;
    else if (aligned[16]) shift_exp = 5'd5;
    else if (aligned[15]) shift_exp = 5'd6;
    else if (aligned[14]) shift_exp = 5'd7;
    else if (aligned[13]) shift_exp = 5'd8;
    else if (aligned[12]) shift_exp = 5'd9;
    else if (aligned[11]) shift_exp = 5'd10;
    else if (aligned[10]) shift_exp = 5'd11;
    else if (aligned[9])  shift_exp = 5'd12;
    else if (aligned[8])  shift_exp = 5'd13;
    else if (aligned[7])  shift_exp = 5'd14;
    else if (aligned[6])  shift_exp = 5'd15;
    else if (aligned[5])  shift_exp = 5'd16;
    else if (aligned[4])  shift_exp = 5'd17;
    else if (aligned[3])  shift_exp = 5'd18;
    else if (aligned[2])  shift_exp = 5'd19;
    else if (aligned[1])  shift_exp = 5'd20;
    else if (aligned[0])  shift_exp = 5'd21;
    else                  shift_exp = 5'd0;
end

// Normalizing
reg [5:0] updated_expo;
reg [4:0] expo;
reg [1:0] flag;
reg [21:0] normalized;
always@(*) begin
    if ((expo_l - shift_exp + carry - BIAS) >= 0) begin
        updated_expo = expo_l - shift_exp + carry - BIAS;
    end else begin
        updated_expo = 6'd0;
    end
    normalized = 22'd0;
    if (updated_expo >= 6'd32) begin
        flag = OVERFLOW;
    end else begin
        expo = updated_expo[4:0];
        if (updated_expo == 6'd0) begin
            flag = UNDERFLOW;
        end else begin
            flag = NORMAL;
            if (carry) normalized = aligned >> 1;
            else normalized = aligned << shift_exp;    
        end
    end 
end

// Mantissa (normal)
wire [9:0] mant = normalized[20:11];

always@(*) begin
    if (flag_zero) result = {sign, 5'h00, 10'h000};
    else begin
        if(flag == NORMAL   ) result = {sign, expo, mant};
        if(flag == OVERFLOW ) result = {sign, 5'h1F, 10'h3FF};
        if(flag == UNDERFLOW) result = {sign, 5'h00, 10'h000};
    end
end
    
endmodule

41_Verilog/tb_f16_fmac_normal_no_grs.v
`timescale 1ns/1ns
module tb_f16_fmac_normal_no_grs;

reg [15:0] x;
reg [15:0] y;
reg [15:0] z;

wire [15:0] result;
reg  [15:0] expected;

 f16_fmac_normal_no_grs u_fmac(
    .x(x),
    .y(y),
    .z(z),
    .result(result)
);

initial begin
    $dumpfile("f16_fmac.vcd");
    $dumpvars(1);
end

initial begin
    x = 16'h0000; y = 16'h0000; z = 16'h0000; expected = 16'h0000;
    
    #10 x = 16'h440D; y = 16'hB9CF; z = 16'hFFFE; expected = 16'hFFFE;    // 00   <------  PASS        <- Z is NaN!  <- Expected is NaN!
    #10 x = 16'h7FFE; y = 16'hFFFE; z = 16'hB8F7; expected = 16'h7FFE;    // 00   <------  FAIL FFFF   <- X is NaN!  <- Y is NaN!  <- Expected is NaN!
    #10 x = 16'h6804; y = 16'h443E; z = 16'h8081; expected = 16'h7042;    // 01   <------  PASS        <- Z is Underflow!
    #10 x = 16'hC3FC; y = 16'hFFFE; z = 16'hFFFE; expected = 16'hFFFE;    // 00   <------  FAIL 7FFF   <- Y is NaN!  <- Z is NaN!  <- Expected is NaN!
    #10 x = 16'h7FFE; y = 16'h0843; z = 16'h086C; expected = 16'h7FFE;    // 00   <------  FAIL 4C41   <- X is NaN!  <- Expected is NaN!
    
    #10 x = 16'h93E3; y = 16'hFFFE; z = 16'hCF84; expected = 16'hFFFE;    // 00   <------  FAIL 5600   <- Y is NaN!  <- Expected is NaN!
    #10 x = 16'h7FFE; y = 16'h00FC; z = 16'hFFFE; expected = 16'h7FFE;    // 00   <------  FAIL FFFE   <- Y is Underflow!  <- X is NaN!  <- Z is NaN!  <- Expected is NaN!
    #10 x = 16'h7D80; y = 16'h4774; z = 16'hBCD7; expected = 16'h7F80;    // 10   <------  FAIL 7FFF   <- X is NaN!  <- Expected is NaN!
    #10 x = 16'h7FFE; y = 16'hFFFE; z = 16'hFFFE; expected = 16'h7FFE;    // 00   <------  FAIL FFFF   <- X is NaN!  <- Y is NaN!  <- Z is NaN!  <- Expected is NaN!
    #10 x = 16'h2F40; y = 16'h0E80; z = 16'h0000; expected = 16'h02F2;    // 00   <------  FAIL 0000   <- Expected is Underflow!
    
    #10 x = 16'h8000; y = 16'h0000; z = 16'hAFBE; expected = 16'hAFBE;    // 00   <------  PASS      
    #10 x = 16'h93F6; y = 16'hC13D; z = 16'h42F6; expected = 16'h42F7;    // 01   <------  PASS      
    #10 x = 16'h53F8; y = 16'h0000; z = 16'h0000; expected = 16'h0000;    // 00   <------  PASS      
    #10 x = 16'h8000; y = 16'h41C6; z = 16'h6BFC; expected = 16'h6BFC;    // 00   <------  PASS      
    #10 x = 16'h9DFE; y = 16'h0000; z = 16'h2EDD; expected = 16'h2EDD;    // 00   <------  PASS      
    
    #10 x = 16'h8000; y = 16'h8B7A; z = 16'h0000; expected = 16'h0000;    // 00   <------  PASS      
    #10 x = 16'h8B1F; y = 16'h1040; z = 16'hC39F; expected = 16'hC39F;    // 01   <------  PASS      
    #10 x = 16'h8000; y = 16'h0000; z = 16'h0000; expected = 16'h0000;    // 00   <------  PASS      
    #10 x = 16'hD409; y = 16'hFCBE; z = 16'h0001; expected = 16'hFEBE;    // 10   <------  FAIL 7FFF   <- Z is Underflow!  <- Y is NaN!  <- Expected is NaN!
    #10 x = 16'h8000; y = 16'h0000; z = 16'hA35F; expected = 16'hA35F;    // 00   <------  PASS      
    
    #10 x = 16'h3077; y = 16'hE882; z = 16'hCC41; expected = 16'hDD4C;    // 01   <------  PASS      
    #10 x = 16'hDFFB; y = 16'h0000; z = 16'h0001; expected = 16'h0001;    // 00   <------  FAIL 0000   <- Z is Underflow!  <- Expected is Underflow!
    #10 x = 16'h8000; y = 16'hC007; z = 16'h6BF1; expected = 16'h6BF1;    // 00   <------  PASS      
    #10 x = 16'h0404; y = 16'h0000; z = 16'hAE10; expected = 16'hAE10;    // 00   <------  PASS      
    #10 x = 16'h8000; y = 16'h13C3; z = 16'h0001; expected = 16'h0001;    // 00   <------  FAIL 0000   <- Z is Underflow!  <- Expected is Underflow!
    
    #10 x = 16'hFA86; y = 16'hFAFB; z = 16'hC2FA; expected = 16'h7C00;    // 05   <------  FAIL 7FFF   <- Expected is +-Inf!
    #10 x = 16'h8000; y = 16'h0000; z = 16'h0001; expected = 16'h0001;    // 00   <------  FAIL 0000   <- Z is Underflow!  <- Expected is Underflow!
    #10 x = 16'h31FF; y = 16'h69EE; z = 16'h03FF; expected = 16'h6072;    // 01   <------  FAIL 6071   <- Z is Underflow!
    #10 x = 16'h8000; y = 16'h0000; z = 16'h7C05; expected = 16'h7E05;    // 10   <------  FAIL 7C05   <- Z is NaN!  <- Expected is NaN!
    #10 x = 16'h873F; y = 16'h3876; z = 16'h4A3F; expected = 16'h4A3F;    // 01   <------  FAIL 4A3E 
    
    #10 x = 16'hC3FF; y = 16'h0000; z = 16'h03FF; expected = 16'h03FF;    // 00   <------  FAIL 0000   <- Z is Underflow!  <- Expected is Underflow!
    #10 x = 16'h8000; y = 16'h4F7B; z = 16'hBBF7; expected = 16'hBBF7;    // 00   <------  PASS      
    #10 x = 16'hDFBB; y = 16'h0000; z = 16'h0081; expected = 16'h0081;    // 00   <------  FAIL 0000   <- Z is Underflow!  <- Expected is Underflow!
    #10 x = 16'h8000; y = 16'hE883; z = 16'h03FF; expected = 16'h03FF;    // 00   <------  FAIL 0000   <- Z is Underflow!  <- Expected is Underflow!
    #10 x = 16'h1382; y = 16'h305A; z = 16'hF7F8; expected = 16'hF7F8;    // 01   <------  PASS      
    
    #10 x = 16'h8000; y = 16'h0000; z = 16'h03FF; expected = 16'h03FF;    // 00   <------  FAIL 0000   <- Z is Underflow!  <- Expected is Underflow!
    #10 x = 16'h41CF; y = 16'h9091; z = 16'h03FE; expected = 16'h9662;    // 01   <------  FAIL 96A1   <- Z is Underflow!
    #10 x = 16'h8000; y = 16'h0000; z = 16'h1000; expected = 16'h1000;    // 00   <------  PASS      
    #10 x = 16'hF240; y = 16'hCBB8; z = 16'h4080; expected = 16'h7C00;    // 05   <------  FAIL 7FFF   <- Expected is +-Inf!
    #10 x = 16'h3328; y = 16'h0000; z = 16'h03FE; expected = 16'h03FE;    // 00   <------  FAIL 0000   <- Z is Underflow!  <- Expected is Underflow!
    
    #10 x = 16'h8000; y = 16'hB3E5; z = 16'hCBEE; expected = 16'hCBEE;    // 00   <------  PASS      
    #10 x = 16'h4CFB; y = 16'h0000; z = 16'h7E62; expected = 16'h7E62;    // 00   <------  PASS        <- Z is NaN!  <- Expected is NaN!
    #10 x = 16'h8000; y = 16'hFF7D; z = 16'h03FE; expected = 16'hFF7D;    // 00   <------  FAIL 0000   <- Z is Underflow!  <- Y is NaN!  <- Expected is NaN!
    #10 x = 16'h1BDF; y = 16'h5D7F; z = 16'hBD0F; expected = 16'h2D95;    // 01   <------  PASS      
    #10 x = 16'h8000; y = 16'h0000; z = 16'h03FE; expected = 16'h03FE;    // 00   <------  FAIL 0000   <- Z is Underflow!  <- Expected is Underflow!
    
    #10 x = 16'h4920; y = 16'h40FB; z = 16'h0400; expected = 16'h4E62;    // 01   <------  FAIL 4E61 
    #10 x = 16'h8000; y = 16'h0000; z = 16'hBD17; expected = 16'hBD17;    // 00   <------  PASS      
    #10 x = 16'hB6D4; y = 16'hDBCC; z = 16'h9C21; expected = 16'h56A8;    // 01   <------  FAIL 56A7 
    #10 x = 16'h98DA; y = 16'h0000; z = 16'h0400; expected = 16'h0400;    // 00   <------  PASS      
    #10 x = 16'h8000; y = 16'h3108; z = 16'h053F; expected = 16'h053F;    // 00   <------  PASS      
    
    #10 $finish;
end

endmodule

41_Verilog/f16_fmac.vcd
$date
	Fri Jun 27 16:01:18 2025
$end
$version
	Icarus Verilog
$end
$timescale
	1ns
$end
$scope module tb_f16_fmac_normal_no_grs $end
$var wire 16 ! result [15:0] $end
$var reg 16 " expected [15:0] $end
$var reg 16 # x [15:0] $end
$var reg 16 $ y [15:0] $end
$var reg 16 % z [15:0] $end
$upscope $end
$enddefinitions $end
$comment Show the parameter values. $end
$dumpall
$end
#0
$dumpvars
b0 %
b0 $
b0 #
b0 "
b0 !
$end
#10
b1111111111111110 !
b1111111111111110 "
b1111111111111110 %
b1011100111001111 $
b100010000001101 #
#20
b1111111111111111 !
b111111111111110 "
b1011100011110111 %
b1111111111111110 $
b111111111111110 #
#30
b111000001000010 !
b111000001000010 "
b1000000010000001 %
b100010000111110 $
b110100000000100 #
#40
b111111111111111 !
b1111111111111110 "
b1111111111111110 %
b1111111111111110 $
b1100001111111100 #
#50
b100110001000001 !
b111111111111110 "
b100001101100 %
b100001000011 $
b111111111111110 #
#60
b101011000000000 !
b1111111111111110 "
b1100111110000100 %
b1111111111111110 $
b1001001111100011 #
#70
b1111111111111110 !
b111111111111110 "
b1111111111111110 %
b11111100 $
b111111111111110 #
#80
b111111111111111 !
b111111110000000 "
b1011110011010111 %
b100011101110100 $
b111110110000000 #
#90
b1111111111111111 !
b111111111111110 "
b1111111111111110 %
b1111111111111110 $
b111111111111110 #
#100
b0 !
b1011110010 "
b0 %
b111010000000 $
b10111101000000 #
#110
b1010111110111110 !
b1010111110111110 "
b1010111110111110 %
b0 $
b1000000000000000 #
#120
b100001011110111 !
b100001011110111 "
b100001011110110 %
b1100000100111101 $
b1001001111110110 #
#130
b0 !
b0 "
b0 %
b0 $
b101001111111000 #
#140
b110101111111100 !
b110101111111100 "
b110101111111100 %
b100000111000110 $
b1000000000000000 #
#150
b10111011011101 !
b10111011011101 "
b10111011011101 %
b0 $
b1001110111111110 #
#160
b0 !
b0 "
b0 %
b1000101101111010 $
b1000000000000000 #
#170
b1100001110011111 !
b1100001110011111 "
b1100001110011111 %
b1000001000000 $
b1000101100011111 #
#180
b0 !
b0 "
b0 %
b0 $
b1000000000000000 #
#190
b111111111111111 !
b1111111010111110 "
b1 %
b1111110010111110 $
b1101010000001001 #
#200
b1010001101011111 !
b1010001101011111 "
b1010001101011111 %
b0 $
b1000000000000000 #
#210
b1101110101001100 !
b1101110101001100 "
b1100110001000001 %
b1110100010000010 $
b11000001110111 #
#220
b0 !
b1 "
b1 %
b0 $
b1101111111111011 #
#230
b110101111110001 !
b110101111110001 "
b110101111110001 %
b1100000000000111 $
b1000000000000000 #
#240
b1010111000010000 !
b1010111000010000 "
b1010111000010000 %
b0 $
b10000000100 #
#250
b0 !
b1 "
b1 %
b1001111000011 $
b1000000000000000 #
#260
b111111111111111 !
b111110000000000 "
b1100001011111010 %
b1111101011111011 $
b1111101010000110 #
#270
b0 !
b1 "
b1 %
b0 $
b1000000000000000 #
#280
b110000001110001 !
b110000001110010 "
b1111111111 %
b110100111101110 $
b11000111111111 #
#290
b111110000000101 !
b111111000000101 "
b111110000000101 %
b0 $
b1000000000000000 #
#300
b100101000111110 !
b100101000111111 "
b100101000111111 %
b11100001110110 $
b1000011100111111 #
#310
b0 !
b1111111111 "
b1111111111 %
b0 $
b1100001111111111 #
#320
b1011101111110111 !
b1011101111110111 "
b1011101111110111 %
b100111101111011 $
b1000000000000000 #
#330
b0 !
b10000001 "
b10000001 %
b0 $
b1101111110111011 #
#340
b1111111111 "
b1111111111 %
b1110100010000011 $
b1000000000000000 #
#350
b1111011111111000 !
b1111011111111000 "
b1111011111111000 %
b11000001011010 $
b1001110000010 #
#360
b0 !
b1111111111 "
b1111111111 %
b0 $
b1000000000000000 #
#370
b1001011010100001 !
b1001011001100010 "
b1111111110 %
b1001000010010001 $
b100000111001111 #
#380
b1000000000000 !
b1000000000000 "
b1000000000000 %
b0 $
b1000000000000000 #
#390
b111111111111111 !
b111110000000000 "
b100000010000000 %
b1100101110111000 $
b1111001001000000 #
#400
b0 !
b1111111110 "
b1111111110 %
b0 $
b11001100101000 #
#410
b1100101111101110 !
b1100101111101110 "
b1100101111101110 %
b1011001111100101 $
b1000000000000000 #
#420
b111111001100010 !
b111111001100010 "
b111111001100010 %
b0 $
b100110011111011 #
#430
b0 !
b1111111101111101 "
b1111111110 %
b1111111101111101 $
b1000000000000000 #
#440
b10110110010101 !
b10110110010101 "
b1011110100001111 %
b101110101111111 $
b1101111011111 #
#450
b0 !
b1111111110 "
b1111111110 %
b0 $
b1000000000000000 #
#460
b100111001100001 !
b100111001100010 "
b10000000000 %
b100000011111011 $
b100100100100000 #
#470
b1011110100010111 !
b1011110100010111 "
b1011110100010111 %
b0 $
b1000000000000000 #
#480
b101011010100111 !
b101011010101000 "
b1001110000100001 %
b1101101111001100 $
b1011011011010100 #
#490
b10000000000 !
b10000000000 "
b10000000000 %
b0 $
b1001100011011010 #
#500
b10100111111 !
b10100111111 "
b10100111111 %
b11000100001000 $
b1000000000000000 #
